offline_ai/__init__.py
offline_ai/cli.py
offline_ai/config.py
offline_ai/main.py
offline_ai/ollama_client.py
offline_ai/uninstaller.py
offline_ai-4.0.0.dist-info/licenses/LICENSE
offline_ai-4.0.0.dist-info/METADATA
offline_ai-4.0.0.dist-info/WHEEL
offline_ai-4.0.0.dist-info/entry_points.txt
offline_ai-4.0.0.dist-info/top_level.txt
offline_ai-4.0.0.dist-info/RECORD
