Metadata-Version: 2.4
Name: offline-ai
Version: 4.0.0
Summary: 🤖 Локальный ИИ-ассистент для терминала с умной установкой без прав администратора
Home-page: https://github.com/ai-terminal/offline-ai
Author: AI Terminal Assistant
Author-email: AI Terminal Assistant <offline-ai@example.com>
Maintainer-email: AI Terminal Assistant <offline-ai@example.com>
License: MIT
Project-URL: Homepage, https://github.com/ai-terminal/offline-ai
Project-URL: Documentation, https://github.com/ai-terminal/offline-ai#readme
Project-URL: Repository, https://github.com/ai-terminal/offline-ai.git
Project-URL: Bug Tracker, https://github.com/ai-terminal/offline-ai/issues
Keywords: ai,artificial-intelligence,terminal,cli,offline,ollama,chatbot,assistant,local-ai,llm
Classifier: Development Status :: 5 - Production/Stable
Classifier: Intended Audience :: Developers
Classifier: Intended Audience :: End Users/Desktop
Classifier: Intended Audience :: Education
Classifier: License :: OSI Approved :: MIT License
Classifier: Operating System :: OS Independent
Classifier: Programming Language :: Python :: 3
Classifier: Programming Language :: Python :: 3.8
Classifier: Programming Language :: Python :: 3.9
Classifier: Programming Language :: Python :: 3.10
Classifier: Programming Language :: Python :: 3.11
Classifier: Programming Language :: Python :: 3.12
Classifier: Topic :: Scientific/Engineering :: Artificial Intelligence
Classifier: Topic :: Software Development :: Libraries :: Python Modules
Classifier: Topic :: Terminals
Classifier: Topic :: Utilities
Classifier: Environment :: Console
Requires-Python: >=3.8
License-File: LICENSE
Requires-Dist: click>=8.0.0
Requires-Dist: rich>=13.0.0
Requires-Dist: requests>=2.25.0
Requires-Dist: pyyaml>=6.0
Requires-Dist: ollama>=0.1.0
Dynamic: author
Dynamic: home-page
Dynamic: license-file
Dynamic: requires-python
